{
  "name": "forbidden witch dragon",
  "egg_description": "This Egg has an aura of benevolent magic.",
  "elements": [
    "light"
  ],
  "rarity": "Epic",
  "region": "Special",
  "dragon_type": "Witch Dragon",
  "body_type": "Draco",
  "food": "Melon",
  "tradeable": false,
  "breeding_tier": 1,
  "forms": [
    "default",
    "undead (default)"
  ],
  "assets": [
    {
      "form_number": "01",
      "gender": "m",
      "stage": "hatchling",
      "color_code": "w",
      "path": "prohibitedwitchdragon_01_m_hatchling_w"
    }
  ],
  "special_actions": [],
  "profile_img_url": "https://static.wikia.nocookie.net/dragon-village-collection/images/4/45/Prohibitedwitchdragon_01_f_adult_w_thumb.png/revision/latest/scale-to-width-down/115?cb=20240419173355",
  "profile_url": "https://dragon-village-collection.fandom.com/wiki/Forbidden_Witch_Dragon",
  "egg_img_url": "https://static.wikia.nocookie.net/dragon-village-collection/images/c/c2/Prohibitedwitchdragon_00_e_egg_w.png/revision/latest?cb=20231129045050"
}