{
  "name": "ophanim",
  "egg_description": "This Egg monitors the movements of all things.",
  "elements": [
    "wind",
    "lightning"
  ],
  "rarity": "Legendary",
  "region": "Sky Kingdom",
  "dragon_type": "Angel Dragon",
  "body_type": "Wyrm",
  "food": "Yggdrasill",
  "tradeable": true,
  "breeding_tier": 0,
  "forms": [
    "default",
    "celestial"
  ],
  "assets": [
    {
      "form_number": "01",
      "gender": "f",
      "stage": "adult",
      "color_code": "y",
      "path": "ophanim_01_f_adult_y"
    },
    {
      "form_number": "01",
      "gender": "f",
      "stage": "hatch",
      "color_code": "y",
      "path": "ophanim_01_f_hatch_y"
    },
    {
      "form_number": "01",
      "gender": "f",
      "stage": "hatchling",
      "color_code": "y",
      "path": "ophanim_01_f_hatchling_y"
    },
    {
      "form_number": "01",
      "gender": "m",
      "stage": "adult",
      "color_code": "y",
      "path": "ophanim_01_m_adult_y"
    },
    {
      "form_number": "01",
      "gender": "m",
      "stage": "hatch",
      "color_code": "y",
      "path": "ophanim_01_m_hatch_y"
    },
    {
      "form_number": "01",
      "gender": "m",
      "stage": "hatchling",
      "color_code": "y",
      "path": "ophanim_01_m_hatchling_y"
    },
    {
      "form_number": "02",
      "gender": "f",
      "stage": "adult",
      "color_code": "w",
      "path": "ophanim_02_f_adult_w"
    },
    {
      "form_number": "02",
      "gender": "f",
      "stage": "hatch",
      "color_code": "w",
      "path": "ophanim_02_f_hatch_w"
    },
    {
      "form_number": "02",
      "gender": "f",
      "stage": "hatchling",
      "color_code": "w",
      "path": "ophanim_02_f_hatchling_w"
    },
    {
      "form_number": "02",
      "gender": "m",
      "stage": "adult",
      "color_code": "w",
      "path": "ophanim_02_m_adult_w"
    },
    {
      "form_number": "02",
      "gender": "m",
      "stage": "hatch",
      "color_code": "w",
      "path": "ophanim_02_m_hatch_w"
    },
    {
      "form_number": "02",
      "gender": "m",
      "stage": "hatchling",
      "color_code": "w",
      "path": "ophanim_02_m_hatchling_w"
    }
  ],
  "special_actions": [],
  "profile_img_url": "https://static.wikia.nocookie.net/dragon-village-collection/images/0/07/Ophanim_01_f_adult_y_thumb.png/revision/latest/scale-to-width-down/115?cb=20240724033801",
  "profile_url": "https://dragon-village-collection.fandom.com/wiki/Ophanim",
  "egg_img_url": "https://static.wikia.nocookie.net/dragon-village-collection/images/b/b0/Ophanim_00_e_egg_y.png/revision/latest?cb=20240724022317"
}