{
  "name": "six-leg horn",
  "egg_description": "This Egg's horn is growing little by little.",
  "elements": [
    "wind",
    "light"
  ],
  "rarity": "Common",
  "region": "East Yutakan",
  "dragon_type": "Horn Dragon",
  "body_type": "Draco",
  "food": "Haunted Pumpkin",
  "tradeable": true,
  "breeding_tier": 4,
  "forms": [
    "default",
    "night sky six-legged horn",
    "sunlight six-legged horn",
    "undead (default)"
  ],
  "assets": [
    {
      "form_number": "01",
      "gender": "f",
      "stage": "adult",
      "color_code": "y",
      "path": "sixleghorn_01_f_adult_y"
    },
    {
      "form_number": "01",
      "gender": "f",
      "stage": "hatch",
      "color_code": "y",
      "path": "sixleghorn_01_f_hatch_y"
    },
    {
      "form_number": "01",
      "gender": "f",
      "stage": "hatchling",
      "color_code": "y",
      "path": "sixleghorn_01_f_hatchling_y"
    },
    {
      "form_number": "01",
      "gender": "m",
      "stage": "adult",
      "color_code": "y",
      "path": "sixleghorn_01_m_adult_y"
    },
    {
      "form_number": "01",
      "gender": "m",
      "stage": "hatch",
      "color_code": "y",
      "path": "sixleghorn_01_m_hatch_y"
    },
    {
      "form_number": "01",
      "gender": "m",
      "stage": "hatchling",
      "color_code": "y",
      "path": "sixleghorn_01_m_hatchling_y"
    },
    {
      "form_number": "02",
      "gender": "f",
      "stage": "adult",
      "color_code": "pb",
      "path": "sixleghorn_02_f_adult_pb"
    },
    {
      "form_number": "02",
      "gender": "f",
      "stage": "hatch",
      "color_code": "pb",
      "path": "sixleghorn_02_f_hatch_pb"
    },
    {
      "form_number": "02",
      "gender": "f",
      "stage": "hatchling",
      "color_code": "pb",
      "path": "sixleghorn_02_f_hatchling_pb"
    },
    {
      "form_number": "02",
      "gender": "m",
      "stage": "adult",
      "color_code": "pb",
      "path": "sixleghorn_02_m_adult_pb"
    },
    {
      "form_number": "02",
      "gender": "m",
      "stage": "hatch",
      "color_code": "pb",
      "path": "sixleghorn_02_m_hatch_pb"
    },
    {
      "form_number": "02",
      "gender": "m",
      "stage": "hatchling",
      "color_code": "pb",
      "path": "sixleghorn_02_m_hatchling_pb"
    },
    {
      "form_number": "03",
      "gender": "f",
      "stage": "adult",
      "color_code": "rp",
      "path": "sixleghorn_03_f_adult_rp"
    },
    {
      "form_number": "03",
      "gender": "f",
      "stage": "hatch",
      "color_code": "rp",
      "path": "sixleghorn_03_f_hatch_rp"
    },
    {
      "form_number": "03",
      "gender": "f",
      "stage": "hatchling",
      "color_code": "rp",
      "path": "sixleghorn_03_f_hatchling_rp"
    },
    {
      "form_number": "03",
      "gender": "m",
      "stage": "adult",
      "color_code": "rp",
      "path": "sixleghorn_03_m_adult_rp"
    },
    {
      "form_number": "03",
      "gender": "m",
      "stage": "hatch",
      "color_code": "rp",
      "path": "sixleghorn_03_m_hatch_rp"
    },
    {
      "form_number": "03",
      "gender": "m",
      "stage": "hatchling",
      "color_code": "rp",
      "path": "sixleghorn_03_m_hatchling_rp"
    }
  ],
  "special_actions": [],
  "profile_img_url": "https://static.wikia.nocookie.net/dragon-village-collection/images/1/16/Sixleghorn_01_f_adult_y_thumb.png/revision/latest/scale-to-width-down/115?cb=20240419173516",
  "profile_url": "https://dragon-village-collection.fandom.com/wiki/Six-Leg_Horn",
  "egg_img_url": "https://static.wikia.nocookie.net/dragon-village-collection/images/b/be/Sixleghorn_00_e_egg_y.png/revision/latest?cb=20240202221554"
}