{
  "dragon": [
    {
      "jealousy_cupid": {
        "name": "jealousy cupid",
        "egg_description": "This Egg symbolizes the Arrow of Jealousy.",
        "elements": [
          "dream"
        ],
        "rarity": "Epic",
        "region": "Special",
        "dragon_type": "Jealousy Dragon",
        "body_type": "Draco",
        "food": "Purple Tulip",
        "tradeable": false,
        "breeding_tier": 5,
        "forms": [
          "default",
          "undead (default)"
        ],
        "assets": [
          {
            "form_number": "01",
            "gender": "f",
            "stage": "adult",
            "color_code": "r",
            "path": "jealousycupid_01_f_adult_r"
          },
          {
            "form_number": "01",
            "gender": "f",
            "stage": "hatch",
            "color_code": "r",
            "path": "jealousycupid_01_f_hatch_r"
          },
          {
            "form_number": "01",
            "gender": "f",
            "stage": "hatchling",
            "color_code": "r",
            "path": "jealousycupid_01_f_hatchling_r"
          },
          {
            "form_number": "01",
            "gender": "m",
            "stage": "adult",
            "color_code": "r",
            "path": "jealousycupid_01_m_adult_r"
          },
          {
            "form_number": "01",
            "gender": "m",
            "stage": "hatch",
            "color_code": "r",
            "path": "jealousycupid_01_m_hatch_r"
          },
          {
            "form_number": "01",
            "gender": "m",
            "stage": "hatchling",
            "color_code": "r",
            "path": "jealousycupid_01_m_hatchling_r"
          }
        ],
        "special_actions": [],
        "profile_img_url": "https://static.wikia.nocookie.net/dragon-village-collection/images/3/33/Jealousycupid_01_f_adult_r_thumb.png/revision/latest/scale-to-width-down/115?cb=20240419173115",
        "profile_url": "https://dragon-village-collection.fandom.com/wiki/Jealousy_Cupid",
        "egg_img_url": "https://static.wikia.nocookie.net/dragon-village-collection/images/7/76/Jealousycupid_00_e_egg_r.png/revision/latest?cb=20230824080639"
      }
    },
    {
      "jet_dragon": {
        "name": "jet dragon",
        "egg_description": "This Egg emits mechanical sounds.",
        "elements": [
          "steel",
          "wind"
        ],
        "rarity": "Common",
        "region": "Sky Kingdom",
        "dragon_type": "Flight Dragon",
        "body_type": "Draco",
        "food": "Yggdrasill",
        "tradeable": true,
        "breeding_tier": 4,
        "forms": [
          "default",
          "arca",
          "signature",
          "undead (default)",
          "undead (signature)"
        ],
        "assets": [
          {
            "form_number": "01",
            "gender": "f",
            "stage": "adult",
            "color_code": "b",
            "path": "jetdragon_01_f_adult_b"
          },
          {
            "form_number": "01",
            "gender": "f",
            "stage": "hatch",
            "color_code": "b",
            "path": "jetdragon_01_f_hatch_b"
          },
          {
            "form_number": "01",
            "gender": "f",
            "stage": "hatchling",
            "color_code": "b",
            "path": "jetdragon_01_f_hatchling_b"
          },
          {
            "form_number": "01",
            "gender": "m",
            "stage": "adult",
            "color_code": "b",
            "path": "jetdragon_01_m_adult_b"
          },
          {
            "form_number": "01",
            "gender": "m",
            "stage": "hatch",
            "color_code": "b",
            "path": "jetdragon_01_m_hatch_b"
          },
          {
            "form_number": "01",
            "gender": "m",
            "stage": "hatchling",
            "color_code": "b",
            "path": "jetdragon_01_m_hatchling_b"
          },
          {
            "form_number": "02",
            "gender": "f",
            "stage": "adult",
            "color_code": "b",
            "path": "jetdragon_02_f_adult_b"
          },
          {
            "form_number": "02",
            "gender": "f",
            "stage": "hatch",
            "color_code": "b",
            "path": "jetdragon_02_f_hatch_b"
          },
          {
            "form_number": "02",
            "gender": "f",
            "stage": "hatchling",
            "color_code": "b",
            "path": "jetdragon_02_f_hatchling_b"
          },
          {
            "form_number": "02",
            "gender": "m",
            "stage": "adult",
            "color_code": "b",
            "path": "jetdragon_02_m_adult_b"
          },
          {
            "form_number": "02",
            "gender": "m",
            "stage": "hatch",
            "color_code": "b",
            "path": "jetdragon_02_m_hatch_b"
          },
          {
            "form_number": "02",
            "gender": "m",
            "stage": "hatchling",
            "color_code": "b",
            "path": "jetdragon_02_m_hatchling_b"
          },
          {
            "form_number": "03",
            "gender": "f",
            "stage": "adult",
            "color_code": "b",
            "path": "jetdragon_03_f_adult_b"
          },
          {
            "form_number": "03",
            "gender": "m",
            "stage": "adult",
            "color_code": "b",
            "path": "jetdragon_03_m_adult_b"
          }
        ],
        "special_actions": [],
        "profile_img_url": "https://static.wikia.nocookie.net/dragon-village-collection/images/e/e2/Jetdragon_01_f_adult_b_thumb.png/revision/latest/scale-to-width-down/115?cb=20240724033759",
        "profile_url": "https://dragon-village-collection.fandom.com/wiki/Jet_Dragon",
        "egg_img_url": "https://static.wikia.nocookie.net/dragon-village-collection/images/b/b3/Jetdragon_00_e_egg_b.png/revision/latest?cb=20240724022317"
      }
    },
    {
      "jima": {
        "name": "jima",
        "egg_description": "This Egg has transparent fins underneath it.",
        "elements": [
          "water"
        ],
        "rarity": "Epic",
        "region": "West Yutakan",
        "dragon_type": "Poison Dragon",
        "body_type": "Draco",
        "food": "Meggison",
        "tradeable": true,
        "breeding_tier": 1,
        "forms": [
          "default",
          "undead (default)"
        ],
        "assets": [
          {
            "form_number": "01",
            "gender": "f",
            "stage": "adult",
            "color_code": "pb",
            "path": "jima_01_f_adult_pb"
          },
          {
            "form_number": "01",
            "gender": "f",
            "stage": "hatch",
            "color_code": "pb",
            "path": "jima_01_f_hatch_pb"
          },
          {
            "form_number": "01",
            "gender": "f",
            "stage": "hatchling",
            "color_code": "pb",
            "path": "jima_01_f_hatchling_pb"
          },
          {
            "form_number": "01",
            "gender": "m",
            "stage": "adult",
            "color_code": "pb",
            "path": "jima_01_m_adult_pb"
          },
          {
            "form_number": "01",
            "gender": "m",
            "stage": "hatch",
            "color_code": "pb",
            "path": "jima_01_m_hatch_pb"
          },
          {
            "form_number": "01",
            "gender": "m",
            "stage": "hatchling",
            "color_code": "pb",
            "path": "jima_01_m_hatchling_pb"
          }
        ],
        "special_actions": [],
        "profile_img_url": "https://static.wikia.nocookie.net/dragon-village-collection/images/7/72/Jima_01_m_adult_pb_thumb.png/revision/latest/scale-to-width-down/115?cb=20240419173115",
        "profile_url": "https://dragon-village-collection.fandom.com/wiki/Jima",
        "egg_img_url": "https://static.wikia.nocookie.net/dragon-village-collection/images/3/3f/Jima_00_e_egg_b.png/revision/latest?cb=20230919103128"
      }
    },
    {
      "jimon": {
        "name": "jimon",
        "egg_description": "This Egg can find its owner.",
        "elements": [
          "earth"
        ],
        "rarity": "Rare",
        "region": "East Yutakan",
        "dragon_type": "Egg Dragon",
        "body_type": "Munia",
        "food": "Jerky",
        "tradeable": true,
        "breeding_tier": 2,
        "forms": [
          "default",
          "undead (default)"
        ],
        "assets": [
          {
            "form_number": "01",
            "gender": "n",
            "stage": "adult",
            "color_code": "rp",
            "path": "jimon_01_n_adult_rp"
          },
          {
            "form_number": "01",
            "gender": "n",
            "stage": "hatch",
            "color_code": "rp",
            "path": "jimon_01_n_hatch_rp"
          },
          {
            "form_number": "01",
            "gender": "n",
            "stage": "hatchling",
            "color_code": "rp",
            "path": "jimon_01_n_hatchling_rp"
          }
        ],
        "special_actions": [],
        "profile_img_url": "https://static.wikia.nocookie.net/dragon-village-collection/images/b/be/Jimon_01_n_adult_rp_thumb.png/revision/latest/scale-to-width-down/115?cb=20240419173115",
        "profile_url": "https://dragon-village-collection.fandom.com/wiki/Jimon",
        "egg_img_url": "https://static.wikia.nocookie.net/dragon-village-collection/images/9/96/Jimon_00_e_egg_rp.png/revision/latest?cb=20230911152907"
      }
    },
    {
      "jujak": {
        "name": "jujak",
        "egg_description": "This Egg emits an aura which signifies the south.",
        "elements": [
          "fire"
        ],
        "rarity": "Rare",
        "region": "West Yutakan",
        "dragon_type": "Reaper Dragon",
        "body_type": "Wyvern",
        "food": "Roast Turkey",
        "tradeable": true,
        "breeding_tier": 2,
        "forms": [
          "default",
          "undead (default)"
        ],
        "assets": [
          {
            "form_number": "01",
            "gender": "f",
            "stage": "adult",
            "color_code": "r",
            "path": "jujag_01_f_adult_r"
          },
          {
            "form_number": "01",
            "gender": "f",
            "stage": "hatch",
            "color_code": "r",
            "path": "jujag_01_f_hatch_r"
          },
          {
            "form_number": "01",
            "gender": "f",
            "stage": "hatchling",
            "color_code": "r",
            "path": "jujag_01_f_hatchling_r"
          },
          {
            "form_number": "01",
            "gender": "m",
            "stage": "adult",
            "color_code": "r",
            "path": "jujag_01_m_adult_r"
          },
          {
            "form_number": "01",
            "gender": "m",
            "stage": "hatch",
            "color_code": "r",
            "path": "jujag_01_m_hatch_r"
          },
          {
            "form_number": "01",
            "gender": "m",
            "stage": "hatchling",
            "color_code": "r",
            "path": "jujag_01_m_hatchling_r"
          }
        ],
        "special_actions": [],
        "profile_img_url": "https://static.wikia.nocookie.net/dragon-village-collection/images/3/36/Jujag_01_m_adult_r_thumb.png/revision/latest/scale-to-width-down/115?cb=20240419173115",
        "profile_url": "https://dragon-village-collection.fandom.com/wiki/Jujak",
        "egg_img_url": "https://static.wikia.nocookie.net/dragon-village-collection/images/4/45/Jujag_00_e_egg_r.png/revision/latest?cb=20231206032147"
      }
    },
    {
      "jump_dragon": {
        "name": "jump dragon",
        "egg_description": "This Egg rarely stays on the ground.",
        "elements": [
          "fire"
        ],
        "rarity": "Uncommon",
        "region": "Deep Sea",
        "dragon_type": "Nomad Dragon",
        "body_type": "Draco",
        "food": "Roast Turkey",
        "tradeable": false,
        "breeding_tier": 3,
        "forms": [
          "default",
          "undead (default)"
        ],
        "assets": [
          {
            "form_number": "01",
            "gender": "f",
            "stage": "adult",
            "color_code": "g",
            "path": "jumpdragon_01_f_adult_g"
          },
          {
            "form_number": "01",
            "gender": "f",
            "stage": "hatch",
            "color_code": "g",
            "path": "jumpdragon_01_f_hatch_g"
          },
          {
            "form_number": "01",
            "gender": "f",
            "stage": "hatchling",
            "color_code": "g",
            "path": "jumpdragon_01_f_hatchling_g"
          },
          {
            "form_number": "01",
            "gender": "m",
            "stage": "adult",
            "color_code": "g",
            "path": "jumpdragon_01_m_adult_g"
          },
          {
            "form_number": "01",
            "gender": "m",
            "stage": "hatch",
            "color_code": "g",
            "path": "jumpdragon_01_m_hatch_g"
          },
          {
            "form_number": "01",
            "gender": "m",
            "stage": "hatchling",
            "color_code": "g",
            "path": "jumpdragon_01_m_hatchling_g"
          }
        ],
        "special_actions": [],
        "profile_img_url": "https://static.wikia.nocookie.net/dragon-village-collection/images/2/29/Jumpdragon_01_m_adult_g_thumb.png/revision/latest/scale-to-width-down/115?cb=20240530035101",
        "profile_url": "https://dragon-village-collection.fandom.com/wiki/Jump_Dragon",
        "egg_img_url": "https://static.wikia.nocookie.net/dragon-village-collection/images/0/08/Jumpdragon_00_e_egg_g.png/revision/latest?cb=20240530022516"
      }
    },
    {
      "kalavinka": {
        "name": "kalavinka",
        "egg_description": "This Egg harbors a grudge.",
        "elements": [
          "dark"
        ],
        "rarity": "Legendary",
        "region": "Deep Sea",
        "dragon_type": "Warrior Dragon",
        "body_type": "Drake",
        "food": "Purple Tulip",
        "tradeable": true,
        "breeding_tier": 0,
        "forms": [
          "default",
          "undead (default)"
        ],
        "assets": [
          {
            "form_number": "01",
            "gender": "f",
            "stage": "adult",
            "color_code": "y",
            "path": "kalavinka_01_f_adult_y"
          },
          {
            "form_number": "01",
            "gender": "f",
            "stage": "hatch",
            "color_code": "y",
            "path": "kalavinka_01_f_hatch_y"
          },
          {
            "form_number": "01",
            "gender": "f",
            "stage": "hatchling",
            "color_code": "y",
            "path": "kalavinka_01_f_hatchling_y"
          },
          {
            "form_number": "01",
            "gender": "m",
            "stage": "adult",
            "color_code": "y",
            "path": "kalavinka_01_m_adult_y"
          },
          {
            "form_number": "01",
            "gender": "m",
            "stage": "hatch",
            "color_code": "y",
            "path": "kalavinka_01_m_hatch_y"
          },
          {
            "form_number": "01",
            "gender": "m",
            "stage": "hatchling",
            "color_code": "y",
            "path": "kalavinka_01_m_hatchling_y"
          }
        ],
        "special_actions": [],
        "profile_img_url": "https://static.wikia.nocookie.net/dragon-village-collection/images/3/3c/Kalavinka_01_f_adult_y_thumb.png/revision/latest/scale-to-width-down/115?cb=20240627033447",
        "profile_url": "https://dragon-village-collection.fandom.com/wiki/Kalavinka",
        "egg_img_url": "https://static.wikia.nocookie.net/dragon-village-collection/images/a/a0/Kalavinka_00_e_egg_y.png/revision/latest?cb=20240627025546"
      }
    },
    {
      "kangarabbit": {
        "name": "kangarabbit",
        "egg_description": "This Egg's pouch is always full.",
        "elements": [
          "earth"
        ],
        "rarity": "Epic",
        "region": "Sky Kingdom",
        "dragon_type": "Animal Dragon",
        "body_type": "Draco",
        "food": "Grapefruit",
        "tradeable": true,
        "breeding_tier": 1,
        "forms": [
          "default",
          "undead (default)"
        ],
        "assets": [
          {
            "form_number": "01",
            "gender": "f",
            "stage": "adult",
            "color_code": "w",
            "path": "kangarabbit_01_f_adult_w"
          },
          {
            "form_number": "01",
            "gender": "f",
            "stage": "hatch",
            "color_code": "w",
            "path": "kangarabbit_01_f_hatch_w"
          },
          {
            "form_number": "01",
            "gender": "f",
            "stage": "hatchling",
            "color_code": "w",
            "path": "kangarabbit_01_f_hatchling_w"
          },
          {
            "form_number": "01",
            "gender": "m",
            "stage": "adult",
            "color_code": "w",
            "path": "kangarabbit_01_m_adult_w"
          },
          {
            "form_number": "01",
            "gender": "m",
            "stage": "hatch",
            "color_code": "w",
            "path": "kangarabbit_01_m_hatch_w"
          },
          {
            "form_number": "01",
            "gender": "m",
            "stage": "hatchling",
            "color_code": "w",
            "path": "kangarabbit_01_m_hatchling_w"
          }
        ],
        "special_actions": [],
        "profile_img_url": "https://static.wikia.nocookie.net/dragon-village-collection/images/b/bd/Kangarabbit_01_m_adult_w_thumb.png/revision/latest/scale-to-width-down/115?cb=20240724033759",
        "profile_url": "https://dragon-village-collection.fandom.com/wiki/Kangarabbit",
        "egg_img_url": "https://static.wikia.nocookie.net/dragon-village-collection/images/8/89/Kangarabbit_00_e_egg_w.png/revision/latest?cb=20240724022317"
      }
    }
  ]
}